auto_stretch/__init__.py
auto_stretch/stretch.py
auto_stretch-0.0.3.dist-info/LICENSE
auto_stretch-0.0.3.dist-info/METADATA
auto_stretch-0.0.3.dist-info/WHEEL
auto_stretch-0.0.3.dist-info/top_level.txt
auto_stretch-0.0.3.dist-info/RECORD
