Metadata-Version: 2.1
Name: auto-stretch
Version: 0.0.3
Summary: Stretch linear astro data for easier visualization.
Home-page: 
Author: Tim Beccue
Author-email: timothybeccue@gmail.com
Classifier: Programming Language :: Python :: 3
Classifier: License :: OSI Approved :: MIT License
Classifier: Operating System :: OS Independent
Requires-Python: >=3.6
License-File: LICENSE
